{
  "project_info": {
    "project_number": "818423677692",
    "firebase_url": "https://hi-malang.firebaseio.com",
    "project_id": "hi-malang",
    "storage_bucket": "hi-malang.appspot.com"
  },
  "client": [
    {
      "client_info": {
        "mobilesdk_app_id": "1:818423677692:android:547dc3d9ee27ef84",
        "android_client_info": {
          "package_name": "ss.com.bannerslidersample"
        }
      },
      "oauth_client": [
        {
          "client_id": "818423677692-n4pi7ool5hc5hq7b5ueequn9c522uai0.apps.googleusercontent.com",
          "client_type": 3
        }
      ],
      "api_key": [
        {
          "current_key": "AIzaSyDiBYydm5dMIxsEsHlzKAtgFPCpvnWgI6s"
        }
      ],
      "services": {
        "analytics_service": {
          "status": 1
        },
        "appinvite_service": {
          "status": 1,
          "other_platform_oauth_client": []
        },
        "ads_service": {
          "status": 2
        }
      }
    }
  ],
  "configuration_version": "1"
}